chatbotkit/__init__.py
chatbotkit-0.0.1.dist-info/METADATA
chatbotkit-0.0.1.dist-info/WHEEL
chatbotkit-0.0.1.dist-info/RECORD
