Metadata-Version: 2.1
Name: chatbotkit
Version: 0.0.1
Summary: The fastest way to build advanced AI chat bots.
License: ISC
Author: Petko D. Petkov
Author-email: pdp@chatbotkit.com
Requires-Python: >=3.8,<4.0
Classifier: License :: OSI Approved
Classifier: Programming Language :: Python :: 3
Classifier: Programming Language :: Python :: 3.8
Classifier: Programming Language :: Python :: 3.9
Classifier: Programming Language :: Python :: 3.10
Classifier: Programming Language :: Python :: 3.11
Requires-Dist: requests (>=2.28.2,<3.0.0)
